[{"connections": ["actionpack","mail"],"dependencies": ["actionpack","mail"],"text": "actionmailer:3.2.13","id": "actionmailer","version": "3.2.13"},{"connections": ["actionmailer","activemodel","activesupport","builder","erubis","journey","rack","rack-cache","rack-test","sprockets","railties"],"dependencies": ["activemodel","activesupport","builder","erubis","journey","rack","rack-cache","rack-test","sprockets"],"text": "actionpack:3.2.13","id": "actionpack","version": "3.2.13"},{"connections": ["activemodel","activesupport","arel","tzinfo"],"dependencies": ["activemodel","activesupport","arel","tzinfo"],"text": "activerecord:3.2.13","id": "activerecord","version": "3.2.13"},{"connections": ["activemodel","activesupport"],"dependencies": ["activemodel","activesupport"],"text": "activeresource:3.2.13","id": "activeresource","version": "3.2.13"},{"connections": ["actionpack","activerecord","activeresource","i18n","multi_json","railties","activemodel"],"dependencies": ["i18n","multi_json"],"text": "activesupport:3.2.13","id": "activesupport","version": "3.2.13"},{"connections": [],"dependencies": [],"text": "bundler:~>1.0","id": "bundler","version": "1.3.4"},{"connections": ["actionpack","activesupport","rack-ssl","rake","rdoc","thor"],"dependencies": ["actionpack","activesupport","rack-ssl","rake","rdoc","thor"],"text": "railties:3.2.13","id": "railties","version": "3.2.13"},{"connections": ["actionmailer","i18n","mime-types","treetop"],"dependencies": ["i18n","mime-types","treetop"],"text": "mail:~>2.5.3","id": "mail","version": "2.5.3"},{"connections": ["actionpack","activerecord","activeresource","activesupport","builder"],"dependencies": ["activesupport","builder"],"text": "activemodel:3.2.13","id": "activemodel","version": "3.2.13"},{"connections": ["actionpack","activemodel"],"dependencies": [],"text": "builder:~>3.0.0","id": "builder","version": "3.0.4"},{"connections": ["actionpack"],"dependencies": [],"text": "erubis:~>2.7.0","id": "erubis","version": "2.7.0"},{"connections": ["actionpack"],"dependencies": [],"text": "journey:~>1.0.4","id": "journey","version": "1.0.4"},{"connections": ["actionpack","rack-cache","rack-test","rack-ssl"],"dependencies": [],"text": "rack:~>1.4.5","id": "rack","version": "1.4.5"},{"connections": ["actionpack","rack"],"dependencies": ["rack"],"text": "rack-cache:~>1.2","id": "rack-cache","version": "1.2"},{"connections": ["actionpack","rack"],"dependencies": ["rack"],"text": "rack-test:~>0.6.1","id": "rack-test","version": "0.6.1"},{"connections": ["actionpack"],"dependencies": [],"text": "sprockets:~>2.2.1","id": "sprockets","version": "2.2.1"},{"connections": ["activerecord"],"dependencies": [],"text": "arel:~>3.0.2","id": "arel","version": "3.0.2"},{"connections": ["activerecord"],"dependencies": [],"text": "tzinfo:~>0.3.29","id": "tzinfo","version": "0.3.29"},{"connections": ["activesupport","mail"],"dependencies": [],"text": "i18n:0.6.1","id": "i18n","version": "0.6.1"},{"connections": ["activesupport"],"dependencies": [],"text": "multi_json:~>1.0","id": "multi_json","version": "1.7.1"},{"connections": ["railties","rack"],"dependencies": ["rack"],"text": "rack-ssl:~>1.3.2","id": "rack-ssl","version": "1.3.2"},{"connections": ["railties"],"dependencies": [],"text": "rake:>=0.8.7","id": "rake","version": "10.0.3"},{"connections": ["railties"],"dependencies": [],"text": "rdoc:~>3.4","id": "rdoc","version": "3.4"},{"connections": ["railties"],"dependencies": [],"text": "thor:<2.0,>=0.14.6","id": "thor","version": "0.17.0"},{"connections": ["mail"],"dependencies": [],"text": "mime-types:~>1.16","id": "mime-types","version": "1.16"},{"connections": ["mail"],"dependencies": [],"text": "treetop:~>1.4.8","id": "treetop","version": "1.4.8"}]